alibabacloud_qualitycheck20190115/__init__.py
alibabacloud_qualitycheck20190115/client.py
alibabacloud_qualitycheck20190115/models/__init__.py
alibabacloud_qualitycheck20190115/models/_add_business_category_request.py
alibabacloud_qualitycheck20190115/models/_add_business_category_response.py
alibabacloud_qualitycheck20190115/models/_add_business_category_response_body.py
alibabacloud_qualitycheck20190115/models/_add_rule_category_request.py
alibabacloud_qualitycheck20190115/models/_add_rule_category_response.py
alibabacloud_qualitycheck20190115/models/_add_rule_category_response_body.py
alibabacloud_qualitycheck20190115/models/_add_rule_v4request.py
alibabacloud_qualitycheck20190115/models/_add_rule_v4response.py
alibabacloud_qualitycheck20190115/models/_add_rule_v4response_body.py
alibabacloud_qualitycheck20190115/models/_apply_ws_token_request.py
alibabacloud_qualitycheck20190115/models/_apply_ws_token_response.py
alibabacloud_qualitycheck20190115/models/_apply_ws_token_response_body.py
alibabacloud_qualitycheck20190115/models/_assign_reviewer_by_session_group_request.py
alibabacloud_qualitycheck20190115/models/_assign_reviewer_by_session_group_response.py
alibabacloud_qualitycheck20190115/models/_assign_reviewer_by_session_group_response_body.py
alibabacloud_qualitycheck20190115/models/_assign_reviewer_request.py
alibabacloud_qualitycheck20190115/models/_assign_reviewer_response.py
alibabacloud_qualitycheck20190115/models/_assign_reviewer_response_body.py
alibabacloud_qualitycheck20190115/models/_batch_submit_review_info_request.py
alibabacloud_qualitycheck20190115/models/_batch_submit_review_info_response.py
alibabacloud_qualitycheck20190115/models/_batch_submit_review_info_response_body.py
alibabacloud_qualitycheck20190115/models/_business_category_basic_info.py
alibabacloud_qualitycheck20190115/models/_condition_basic_info.py
alibabacloud_qualitycheck20190115/models/_create_asr_vocab_request.py
alibabacloud_qualitycheck20190115-8.5.1.dist-info/LICENSE
alibabacloud_qualitycheck20190115-8.5.1.dist-info/METADATA
alibabacloud_qualitycheck20190115-8.5.1.dist-info/WHEEL
alibabacloud_qualitycheck20190115-8.5.1.dist-info/top_level.txt
alibabacloud_qualitycheck20190115-8.5.1.dist-info/RECORD
